{
  "restaurantName": "Ahumados en el Barril",
  "menu": [
    { "id": "picaditas-probar", "name": "PARA PROBAR", "category": "PICADITAS CERDO", "price": 2.5, "pricingMode": "fixed" },
    { "id": "picaditas-picar", "name": "PARA PICAR", "category": "PICADITAS CERDO", "price": 3.5, "pricingMode": "fixed" },
    { "id": "picaditas-gozar", "name": "PARA GOZAR", "category": "PICADITAS CERDO", "price": 5, "pricingMode": "fixed" },
    { "id": "picaditas-familiar", "name": "FAMILIAR", "category": "PICADITAS CERDO", "price": 10, "pricingMode": "fixed" },
    { "id": "picaditas-fritas", "name": "FRITAS", "category": "PICADITAS CERDO", "price": 1, "pricingMode": "fixed" },
    { "id": "picaditas-patacones", "name": "PATACONES", "category": "PICADITAS CERDO", "price": 1, "pricingMode": "fixed" },
    { "id": "bebida-agua", "name": "AGUA NATURAL", "category": "BEBIDAS", "price": 0.5, "pricingMode": "fixed" },
    { "id": "bebida-jugo-frozen", "name": "JUGO FROZEN", "category": "BEBIDAS", "price": 1, "pricingMode": "fixed" },
    { "id": "bebida-gaseosa-personal", "name": "GASEOSA PERSONAL", "category": "BEBIDAS", "price": 0.75, "pricingMode": "fixed" },
    { "id": "bebida-fuze-te", "name": "FUZE TE", "category": "BEBIDAS", "price": 0.75, "pricingMode": "fixed" },
    { "id": "bebida-del-valle", "name": "DEL VALLE", "category": "BEBIDAS", "price": 0.5, "pricingMode": "fixed" },
    { "id": "bebida-gaseosa-1l", "name": "GASEOSA DE 1L", "category": "BEBIDAS", "price": 1.75, "pricingMode": "fixed" },
    { "id": "bebida-cerveza-sol", "name": "CERVEZA SOL", "category": "BEBIDAS", "price": 2.25, "pricingMode": "fixed" },
    { "id": "bebida-cerveza-club", "name": "CERVEZA CLUB", "category": "BEBIDAS", "price": 2.25, "pricingMode": "fixed" },
    { "id": "bebida-solveza", "name": "SOLVEZA", "category": "BEBIDAS", "price": 2.5, "pricingMode": "fixed" },
    { "id": "bebida-jarra-sangria", "name": "JARRA DE SANGRIA", "category": "BEBIDAS", "price": 10, "pricingMode": "fixed" },
    { "id": "fuerte-taco-taco", "name": "TACO TACO", "category": "PLATOS FUERTES", "price": 2.75, "pricingMode": "fixed" },
    { "id": "fuerte-costillitas", "name": "COSTILLITAS", "category": "PLATOS FUERTES", "price": 5, "pricingMode": "fixed" },
    { "id": "fuerte-come-solo", "name": "COME SOLO", "category": "PLATOS FUERTES", "price": 4.5, "pricingMode": "fixed" },
    { "id": "fuerte-come-bien", "name": "COME BIEN", "category": "PLATOS FUERTES", "price": 5.5, "pricingMode": "fixed" },
    { "id": "fuerte-bestia", "name": "PICADITA ESPECIAL LA BESTIA", "category": "PLATOS FUERTES", "price": 24, "pricingMode": "fixed" },
    { "id": "extra-chicloso", "name": "PORCION DE CHICLOSO", "category": "PORCIONES EXTRA", "price": 2.5, "pricingMode": "fixed" },
    { "id": "extra-moro", "name": "PORCION DE MORO", "category": "PORCIONES EXTRA", "price": 2, "pricingMode": "fixed" },
    { "id": "extra-choclo", "name": "PORCION DE CHOCLO", "category": "PORCIONES EXTRA", "price": 2, "pricingMode": "fixed" },
    { "id": "extra-pan", "name": "PORCION DE PAN", "category": "PORCIONES EXTRA", "price": 0.5, "pricingMode": "fixed" },
    { "id": "extra-ensalada", "name": "PORCION DE ENSALADA", "category": "PORCIONES EXTRA", "price": 0.5, "pricingMode": "fixed" },
    { "id": "extra-papa", "name": "PORCION DE PAPA", "category": "PORCIONES EXTRA", "price": 1, "pricingMode": "fixed" },
    { "id": "extra-pina", "name": "PORCION DE PINA", "category": "PORCIONES EXTRA", "price": 1, "pricingMode": "fixed" },
    { "id": "extra-c-parri", "name": "PORCION DE C. PARRI", "category": "PORCIONES EXTRA", "price": 1, "pricingMode": "fixed" },
    { "id": "extra-c-f-hierb", "name": "PORCION DE C. F. HIERB", "category": "PORCIONES EXTRA", "price": 1.5, "pricingMode": "fixed" },
    { "id": "extra-cerdo", "name": "PORCION DE CERDO", "category": "PORCIONES EXTRA", "price": 2, "pricingMode": "fixed" },
    { "id": "extra-costilla", "name": "PORCION DE COSTILLA", "category": "PORCIONES EXTRA", "price": 2.5, "pricingMode": "fixed" },
    { "id": "extra-longaniza", "name": "PORCION DE LONGANIZA", "category": "PORCIONES EXTRA", "price": 1.25, "pricingMode": "fixed" },
    { "id": "extra-panceta", "name": "PORCION DE PANCETA", "category": "PORCIONES EXTRA", "price": 3, "pricingMode": "fixed" },
    { "id": "extra-papas-fritas", "name": "PORCION DE PAPAS FRITAS", "category": "PORCIONES EXTRA", "price": 2, "pricingMode": "fixed" },
    { "id": "extra-patacones", "name": "PORCION DE PATACONES", "category": "PORCIONES EXTRA", "price": 2, "pricingMode": "fixed" },
    { "id": "entrada-salchipapa", "name": "SALCHIPAPA", "category": "ENTRADAS Y ACOMPAÑANTES", "price": 3, "pricingMode": "fixed" },
    { "id": "entrada-patacones-chicle", "name": "PATACONES CON CHICLE", "category": "ENTRADAS Y ACOMPAÑANTES", "price": 3, "pricingMode": "fixed" },
    { "id": "entrada-papas-cheddar", "name": "PAPAS CON CHEDDAR", "category": "ENTRADAS Y ACOMPAÑANTES", "price": 3, "pricingMode": "fixed" },
    { "id": "entrada-maduro-chicle", "name": "MADURO CON CHICLE", "category": "ENTRADAS Y ACOMPAÑANTES", "price": 3, "pricingMode": "fixed" },
    { "id": "corte-medallones-bondiola", "name": "MEDALLONES DE BONDIOLA", "category": "CORTES AHUMADOS", "price": 0, "pricingMode": "weight", "weightFormula": "corte-ahumado" },
    { "id": "corte-chuleta-cerdo", "name": "CHULETA DE CERDO", "category": "CORTES AHUMADOS", "price": 0, "pricingMode": "weight", "weightFormula": "corte-ahumado" },
    { "id": "corte-lomo-fino", "name": "LOMO FINO", "category": "CORTES AHUMADOS", "price": 0, "pricingMode": "weight", "weightFormula": "corte-ahumado" },
    { "id": "corte-costillas-san-luis", "name": "COSTILLAS SAN LUIS", "category": "CORTES AHUMADOS", "price": 0, "pricingMode": "weight", "weightFormula": "corte-ahumado" },
    { "id": "corte-costillas-baby-back", "name": "COSTILLAS BABY BACK", "category": "CORTES AHUMADOS", "price": 0, "pricingMode": "weight", "weightFormula": "corte-ahumado" },
    { "id": "corte-matambre-cerdo", "name": "MATAMBRE", "category": "CORTES AHUMADOS", "price": 0, "pricingMode": "weight", "weightFormula": "corte-ahumado" },
    { "id": "corte-filete-pechuga-pollo", "name": "FILETE DE PECHUGA DE POLLO", "category": "CORTES AHUMADOS", "price": 0, "pricingMode": "weight", "weightFormula": "corte-pechuga-pollo" },
    { "id": "corte-panceta-cerdo", "name": "PANCETA DE CERDO", "category": "CORTES AHUMADOS", "price": 0, "pricingMode": "weight", "weightFormula": "corte-panceta" },
    { "id": "corte-t-bone-steak", "name": "T BONE STEAK", "category": "CORTES - RES ASADA", "price": 0, "pricingMode": "weight", "weightFormula": "corte-t-bone" }
  ],
  "orders": []
}
